WeatherPy/__init__.py
WeatherPy/weather_utils.py
Weatherpy_1-0.4.dist-info/LICENSE
Weatherpy_1-0.4.dist-info/METADATA
Weatherpy_1-0.4.dist-info/WHEEL
Weatherpy_1-0.4.dist-info/top_level.txt
Weatherpy_1-0.4.dist-info/RECORD
