Metadata-Version: 2.1
Name: Weatherpy-1
Version: 0.4
Summary: Python Wrapper For Weather API
Author: Deep Shah
Author-email: dpshah2307@gmail.com
Keywords: python,weather,weather api,weather forecast,weatherpy
Classifier: Development Status :: 1 - Planning
Classifier: Intended Audience :: Developers
Classifier: Programming Language :: Python :: 3
Classifier: Operating System :: Unix
Classifier: Operating System :: MacOS :: MacOS X
Classifier: Operating System :: Microsoft :: Windows
License-File: LICENSE
Requires-Dist: requests
